PyShellyControl/Shelly3EM.py
PyShellyControl/ShellyDevice.py
PyShellyControl/ShellyDimmer2.py
PyShellyControl/ShellyDuoE27GU10.py
PyShellyControl/ShellyPlug.py
PyShellyControl/ShellyPlus1.py
PyShellyControl/ShellyPlus1PM.py
PyShellyControl/ShellyPlus2PM.py
PyShellyControl/ShellyPro1.py
PyShellyControl/ShellyPro1PM.py
PyShellyControl/ShellyPro2.py
PyShellyControl/ShellyPro2PM.py
PyShellyControl/ShellyPro3.py
PyShellyControl/ShellyPro4PM.py
PyShellyControl/ShellyRGBW2.py
PyShellyControl/ShellyTRV.py
PyShellyControl/ShellyUni.py
PyShellyControl/ShellyVintage.py
PyShellyControl/__init__.py
PyShellyControl-0.1.0.dist-info/LICENSE
PyShellyControl-0.1.0.dist-info/METADATA
PyShellyControl-0.1.0.dist-info/WHEEL
PyShellyControl-0.1.0.dist-info/top_level.txt
PyShellyControl-0.1.0.dist-info/RECORD
