Metadata-Version: 2.1
Name: PyShellyControl
Version: 0.1.0
Summary: A python library for controlling shelly devices
Home-page: https://github.com/Michdo93/PyShellyControl
Author: Michael Christian Dörflinger
Author-email: michaeldoerflinger93@gmail.com
Classifier: Programming Language :: Python :: 3
Classifier: License :: OSI Approved :: MIT License
Classifier: Operating System :: OS Independent
Requires-Python: >=3.6
License-File: LICENSE
Requires-Dist: requests
Requires-Dist: paho-mqtt
